{
  "status": "published",
  "id": "98bd6f8f-39a8-463c-b30b-2859ebd45541",
  "created": 1775233696918,
  "name": "Computer Vision",
  "elements": [
    {
      "id": "051996d9-55de-4769-bdfa-80888958a22b",
      "fillStyle": "solid",
      "strokeWidth": 0,
      "strokeStyle": "solid",
      "roughness": 0,
      "opacity": 100,
      "angle": 0,
      "strokeColor": "transparent",
      "backgroundColor": "#50e6ff",
      "seed": 752399557,
      "version": 1,
      "versionNonce": 675622095,
      "isDeleted": false,
      "groupIds": [
        "195a90c3-5403-407a-b7b7-8333a26b1f17"
      ],
      "frameId": null,
      "index": "a0",
      "roundness": null,
      "boundElements": null,
      "updated": 1775233696917,
      "link": null,
      "locked": false,
      "type": "line",
      "x": 2.0977777777777775,
      "y": 17.39022222222222,
      "width": 16.53688888888889,
      "height": 17.39022222222222,
      "points": [
        [
          0,
          0
        ],
        [
          -0.4034280429218491,
          -0.040669009741321815
        ],
        [
          -0.7791822490098822,
          -0.15730962070041224
        ],
        [
          -1.1192129908667752,
          -0.3418722054799351
        ],
        [
          -1.4154706410952036,
          -0.5863071366825731
        ],
        [
          -1.6599055722978429,
          -0.8825647869110026
        ],
        [
          -1.8444681570773676,
          -1.2225955287678938
        ],
        [
          -1.961108768036454,
          -1.5983497348559264
        ],
        [
          -2.0017777777777774,
          -2.0017777777777765
        ],
        [
          -2.0017777777777774,
          -15.388444444444445
        ],
        [
          -1.9611087680364545,
          -15.791872487366291
        ],
        [
          -1.844468157077368,
          -16.167626693454327
        ],
        [
          -1.659905572297843,
          -16.50765743531122
        ],
        [
          -1.4154706410952045,
          -16.80391508553965
        ],
        [
          -1.119212990866776,
          -17.048350016742287
        ],
        [
          -0.779182249009883,
          -17.23291260152181
        ],
        [
          -0.40342804292184964,
          -17.3495532124809
        ],
        [
          -3.9474596431116675e-16,
          -17.39022222222222
        ],
        [
          12.533333333333333,
          -17.39022222222222
        ],
        [
          12.93676137625518,
          -17.3495532124809
        ],
        [
          13.312515582343217,
          -17.23291260152181
        ],
        [
          13.652546324200111,
          -17.048350016742287
        ],
        [
          13.948803974428538,
          -16.80391508553965
        ],
        [
          14.193238905631176,
          -16.50765743531122
        ],
        [
          14.377801490410702,
          -16.167626693454327
        ],
        [
          14.494442101369788,
          -15.791872487366291
        ],
        [
          14.53511111111111,
          -15.388444444444445
        ],
        [
          14.494442101369788,
          -14.985016401522595
        ],
        [
          14.377801490410702,
          -14.609262195434562
        ],
        [
          14.193238905631176,
          -14.269231453577667
        ],
        [
          13.948803974428538,
          -13.972973803349241
        ],
        [
          13.652546324200108,
          -13.7285388721466
        ],
        [
          13.312515582343217,
          -13.543976287367075
        ],
        [
          12.936761376255184,
          -13.42733567640799
        ],
        [
          12.533333333333333,
          -13.386666666666667
        ],
        [
          2.001777777777778,
          -13.386666666666667
        ],
        [
          2.001777777777778,
          -2.008888888888887
        ],
        [
          1.992641851056991,
          -1.8105498312333987
        ],
        [
          1.9641788836778344,
          -1.6155162845998947
        ],
        [
          1.9169327598755503,
          -1.425111254721609
        ],
        [
          1.8514473638853814,
          -1.2406577473317857
        ],
        [
          1.7682665799425703,
          -1.0634787681636686
        ],
        [
          1.6679342922823595,
          -0.8948973229504986
        ],
        [
          1.5509943851399925,
          -0.7362364174255163
        ],
        [
          1.4179907427507124,
          -0.5888190573219686
        ],
        [
          1.2710459521568904,
          -0.4552934962257748
        ],
        [
          1.1128007234131054,
          -0.33779169877441795
        ],
        [
          0.9445761252729079,
          -0.23686223727847908
        ],
        [
          0.7676932264898484,
          -0.1530536840485139
        ],
        [
          0.5834730958174781,
          -0.08691461139511603
        ],
        [
          0.39323680200934774,
          -0.03899359162884745
        ],
        [
          0.19830541381900818,
          -0.00983919706027968
        ],
        [
          1.0263395072090336e-14,
          0
        ],
        [
          0,
          0
        ]
      ]
    },
    {
      "id": "fbd89b6f-a6aa-4784-a1ad-83a167d62e71",
      "fillStyle": "solid",
      "strokeWidth": 0,
      "strokeStyle": "solid",
      "roughness": 0,
      "opacity": 100,
      "angle": 0,
      "strokeColor": "transparent",
      "backgroundColor": "#50e6ff",
      "seed": 160651239,
      "version": 1,
      "versionNonce": 869134707,
      "isDeleted": false,
      "groupIds": [
        "195a90c3-5403-407a-b7b7-8333a26b1f17"
      ],
      "frameId": null,
      "index": "a0",
      "roundness": null,
      "boundElements": null,
      "updated": 1775233696918,
      "link": null,
      "locked": false,
      "type": "line",
      "x": 63.903999999999996,
      "y": 15.388444444444445,
      "width": 16.536888888888914,
      "height": 17.383111111111113,
      "points": [
        [
          0,
          0
        ],
        [
          0,
          -13.386666666666668
        ],
        [
          -0.04126418086430779,
          -13.78978141056406
        ],
        [
          -0.15824937916880166,
          -14.165231296749345
        ],
        [
          -0.34294623495883214,
          -14.505006965267837
        ],
        [
          -0.5873453882797118,
          -14.801099056164853
        ],
        [
          -0.8834374791767408,
          -15.045498209485707
        ],
        [
          -1.2232131476952317,
          -15.230195065275712
        ],
        [
          -1.5986630338805095,
          -15.347180263580187
        ],
        [
          -2.0017777777778747,
          -15.388444444444445
        ],
        [
          -14.535111111111107,
          -15.388444444444445
        ],
        [
          -14.938539154032954,
          -15.347775434703124
        ],
        [
          -15.31429336012099,
          -15.231134823744036
        ],
        [
          -15.654324101977888,
          -15.04657223896451
        ],
        [
          -15.950581752206315,
          -14.802137307761871
        ],
        [
          -16.195016683408948,
          -14.505879657533441
        ],
        [
          -16.37957926818848,
          -14.16584891567655
        ],
        [
          -16.496219879147564,
          -13.790094709588516
        ],
        [
          -16.53688888888889,
          -13.386666666666668
        ],
        [
          -16.496219879147564,
          -12.983238623744818
        ],
        [
          -16.37957926818848,
          -12.607484417656785
        ],
        [
          -16.195016683408955,
          -12.26745367579989
        ],
        [
          -15.950581752206308,
          -11.971196025571464
        ],
        [
          -15.654324101977888,
          -11.726761094368824
        ],
        [
          -15.31429336012099,
          -11.5421985095893
        ],
        [
          -14.938539154032954,
          -11.425557898630213
        ],
        [
          -14.535111111111107,
          -11.38488888888889
        ],
        [
          -4.003555555555547,
          -11.38488888888889
        ],
        [
          -4.003555555555547,
          -0.007111111111110327
        ],
        [
          -3.9628865458142095,
          0.3963169318107399
        ],
        [
          -3.8462459348551317,
          0.7720711378987756
        ],
        [
          -3.661683350075615,
          1.1121018797556668
        ],
        [
          -3.417248418872974,
          1.4083595299840965
        ],
        [
          -3.120990768644535,
          1.6527944611867345
        ],
        [
          -2.78096002678765,
          1.8373570459662605
        ],
        [
          -2.4052058206996207,
          1.9539976569253446
        ],
        [
          -2.001777777777761,
          1.9946666666666695
        ],
        [
          -1.5983497348559137,
          1.9539976569253477
        ],
        [
          -1.2225955287678718,
          1.8373570459662636
        ],
        [
          -0.8825647869109742,
          1.6527944611867376
        ],
        [
          -0.5863071366825477,
          1.4083595299840932
        ],
        [
          -0.34187220547990665,
          1.1121018797556668
        ],
        [
          -0.15730962070039015,
          0.7720711378987725
        ],
        [
          -0.04066900974129971,
          0.3963169318107399
        ],
        [
          2.5263741715914672e-14,
          -0.007111111111110327
        ],
        [
          0,
          0
        ]
      ]
    },
    {
      "id": "2fb33bbc-868a-4260-b172-8b3784889c0f",
      "fillStyle": "solid",
      "strokeWidth": 0,
      "strokeStyle": "solid",
      "roughness": 0,
      "opacity": 100,
      "angle": 0,
      "strokeColor": "transparent",
      "backgroundColor": "#50e6ff",
      "seed": 542970953,
      "version": 1,
      "versionNonce": 1022723116,
      "isDeleted": false,
      "groupIds": [
        "195a90c3-5403-407a-b7b7-8333a26b1f17"
      ],
      "frameId": null,
      "index": "a0",
      "roundness": null,
      "boundElements": null,
      "updated": 1775233696918,
      "link": null,
      "locked": false,
      "type": "line",
      "x": 16.63288888888889,
      "y": 61.998222222222225,
      "width": 16.53688888888889,
      "height": 17.383111111111113,
      "points": [
        [
          0,
          0
        ],
        [
          -0.04066900974132497,
          -0.4034280429218471
        ],
        [
          -0.15730962070040908,
          -0.7791822490098764
        ],
        [
          -0.3418722054799351,
          -1.119212990866774
        ],
        [
          -0.5863071366825731,
          -1.4154706410952005
        ],
        [
          -0.8825647869110026,
          -1.6599055722978289
        ],
        [
          -1.2225955287678938,
          -1.8444681570773456
        ],
        [
          -1.5983497348559264,
          -1.9611087680364359
        ],
        [
          -2.0017777777777765,
          -2.001777777777761
        ],
        [
          -12.533333333333331,
          -2.001777777777761
        ],
        [
          -12.533333333333331,
          -13.379555555555548
        ],
        [
          -12.574002343074655,
          -13.7829835984774
        ],
        [
          -12.690642954033741,
          -14.158737804565432
        ],
        [
          -12.875205538813265,
          -14.498768546422315
        ],
        [
          -13.119640470015906,
          -14.795026196650754
        ],
        [
          -13.415898120244334,
          -15.039461127853397
        ],
        [
          -13.755928862101229,
          -15.224023712632919
        ],
        [
          -14.131683068189261,
          -15.340664323592003
        ],
        [
          -14.53511111111111,
          -15.381333333333329
        ],
        [
          -14.938539154032958,
          -15.340664323592003
        ],
        [
          -15.314293360120994,
          -15.224023712632919
        ],
        [
          -15.654324101977885,
          -15.039461127853397
        ],
        [
          -15.950581752206315,
          -14.795026196650749
        ],
        [
          -16.19501668340895,
          -14.498768546422323
        ],
        [
          -16.37957926818848,
          -14.158737804565432
        ],
        [
          -16.496219879147567,
          -13.782983598477395
        ],
        [
          -16.53688888888889,
          -13.379555555555548
        ],
        [
          -16.53688888888889,
          0.0071111111111198015
        ],
        [
          -16.49498146499055,
          0.40943627213353767
        ],
        [
          -16.377536878466117,
          0.7840112265929898
        ],
        [
          -16.19256445372522,
          1.1228551023868045
        ],
        [
          -15.948073515177494,
          1.4179870274123232
        ],
        [
          -15.652073387232578,
          1.6614261295668358
        ],
        [
          -15.312573394300111,
          1.8451915367477214
        ],
        [
          -14.937582860789723,
          1.9613023768522453
        ],
        [
          -14.535111111111057,
          2.0017777777777863
        ],
        [
          -2.0017777777777765,
          2.0017777777777863
        ],
        [
          -1.5983497348559297,
          1.9611087680364485
        ],
        [
          -1.2225955287678971,
          1.8444681570773582
        ],
        [
          -0.8825647869110026,
          1.6599055722978289
        ],
        [
          -0.5863071366825762,
          1.4154706410951878
        ],
        [
          -0.34187220547993824,
          1.1192129908667614
        ],
        [
          -0.15730962070041224,
          0.7791822490098764
        ],
        [
          -0.04066900974132813,
          0.4034280429218471
        ],
        [
          -3.157967714489334e-15,
          -1.2631870857957336e-14
        ],
        [
          0,
          0
        ]
      ]
    },
    {
      "id": "79f3f2c9-3e9e-473e-804c-779bef0b81a7",
      "fillStyle": "solid",
      "strokeWidth": 0,
      "strokeStyle": "solid",
      "roughness": 0,
      "opacity": 100,
      "angle": 0,
      "strokeColor": "transparent",
      "backgroundColor": "#50e6ff",
      "seed": 272113537,
      "version": 1,
      "versionNonce": 426942727,
      "isDeleted": false,
      "groupIds": [
        "195a90c3-5403-407a-b7b7-8333a26b1f17"
      ],
      "frameId": null,
      "index": "a0",
      "roundness": null,
      "boundElements": null,
      "updated": 1775233696918,
      "link": null,
      "locked": false,
      "type": "line",
      "x": 63.903999999999996,
      "y": 61.998222222222225,
      "width": 16.53688888888889,
      "height": 17.383111111111127,
      "points": [
        [
          0,
          0
        ],
        [
          0,
          -13.386666666666668
        ],
        [
          -0.04066900974131234,
          -13.790094709588521
        ],
        [
          -0.15730962070040277,
          -14.16584891567655
        ],
        [
          -0.34187220547994457,
          -14.505879657533448
        ],
        [
          -0.5863071366825731,
          -14.802137307761882
        ],
        [
          -0.8825647869109995,
          -15.04657223896451
        ],
        [
          -1.2225955287678971,
          -15.23113482374404
        ],
        [
          -1.5983497348559264,
          -15.347775434703129
        ],
        [
          -2.0017777777777863,
          -15.388444444444447
        ],
        [
          -2.405205820699633,
          -15.347775434703129
        ],
        [
          -2.7809600267876626,
          -15.23113482374404
        ],
        [
          -3.1209907686445604,
          -15.046572238964515
        ],
        [
          -3.417248418872987,
          -14.802137307761882
        ],
        [
          -3.6616833500756405,
          -14.505879657533448
        ],
        [
          -3.846245934855157,
          -14.16584891567655
        ],
        [
          -3.9628865458142473,
          -13.790094709588516
        ],
        [
          -4.003555555555573,
          -13.386666666666668
        ],
        [
          -4.003555555555573,
          -2.0088888888888934
        ],
        [
          -14.535111111111107,
          -2.0088888888888934
        ],
        [
          -14.938539154032954,
          -1.968219879147581
        ],
        [
          -15.31429336012099,
          -1.8515792681884906
        ],
        [
          -15.654324101977888,
          -1.6670166834089488
        ],
        [
          -15.950581752206315,
          -1.4225817522063202
        ],
        [
          -16.195016683408955,
          -1.1263241019778938
        ],
        [
          -16.37957926818848,
          -0.7862933601209836
        ],
        [
          -16.496219879147564,
          -0.41053915403295427
        ],
        [
          -16.53688888888889,
          -0.007111111111107169
        ],
        [
          -16.496219879147564,
          0.3963169318107399
        ],
        [
          -16.37957926818848,
          0.7720711378987819
        ],
        [
          -16.195016683408955,
          1.1121018797556668
        ],
        [
          -15.950581752206308,
          1.4083595299840932
        ],
        [
          -15.654324101977888,
          1.6527944611867345
        ],
        [
          -15.31429336012099,
          1.8373570459662636
        ],
        [
          -14.938539154032954,
          1.953997656925354
        ],
        [
          -14.535111111111107,
          1.994666666666679
        ],
        [
          -2.0017777777777734,
          1.994666666666679
        ],
        [
          -1.5996167365329685,
          1.9535994799880931
        ],
        [
          -1.224928128432882,
          1.8371456424297068
        ],
        [
          -0.8856812824798099,
          1.6532461727664691
        ],
        [
          -0.589845527676074,
          1.4098420897733048
        ],
        [
          -0.34539019302390744,
          1.1148744122251502
        ],
        [
          -0.1602846075256568,
          0.7762841588969169
        ],
        [
          -0.042498100183593124,
          0.40201234856356727
        ],
        [
          -1.2631870857957336e-14,
          0
        ],
        [
          0,
          0
        ]
      ]
    },
    {
      "id": "2a150f51-d7bc-4d56-802d-12c6182c7e78",
      "fillStyle": "solid",
      "strokeWidth": 0,
      "strokeStyle": "solid",
      "roughness": 0,
      "opacity": 100,
      "angle": 0,
      "strokeColor": "transparent",
      "backgroundColor": "#0078d4",
      "seed": 1401329434,
      "version": 1,
      "versionNonce": 1072027695,
      "isDeleted": false,
      "groupIds": [
        "195a90c3-5403-407a-b7b7-8333a26b1f17"
      ],
      "frameId": null,
      "index": "a0",
      "roundness": null,
      "boundElements": null,
      "updated": 1775233696918,
      "link": null,
      "locked": false,
      "type": "ellipse",
      "x": 5.728000000000002,
      "y": 6.371555555555554,
      "width": 50.87288888888889,
      "height": 50.872888888888895
    },
    {
      "id": "3dd5df75-ce27-4a60-8e22-8f185e954dfc",
      "fillStyle": "solid",
      "strokeWidth": 0,
      "strokeStyle": "solid",
      "roughness": 0,
      "opacity": 100,
      "angle": 0,
      "strokeColor": "transparent",
      "backgroundColor": "#5ea0ef",
      "seed": 246715104,
      "version": 1,
      "versionNonce": 1894253347,
      "isDeleted": false,
      "groupIds": [
        "195a90c3-5403-407a-b7b7-8333a26b1f17"
      ],
      "frameId": null,
      "index": "a0",
      "roundness": null,
      "boundElements": null,
      "updated": 1775233696918,
      "link": null,
      "locked": false,
      "type": "ellipse",
      "x": 9.184,
      "y": 10.314666666666666,
      "width": 43.96088888888889,
      "height": 43.96088888888889
    },
    {
      "id": "bd946242-6659-4d69-8e25-121f629f931d",
      "fillStyle": "solid",
      "strokeWidth": 0,
      "strokeStyle": "solid",
      "roughness": 0,
      "opacity": 100,
      "angle": 0,
      "strokeColor": "transparent",
      "backgroundColor": "#5ea0ef",
      "seed": 1128492472,
      "version": 1,
      "versionNonce": 1529795558,
      "isDeleted": false,
      "groupIds": [
        "195a90c3-5403-407a-b7b7-8333a26b1f17"
      ],
      "frameId": null,
      "index": "a0",
      "roundness": null,
      "boundElements": null,
      "updated": 1775233696918,
      "link": null,
      "locked": false,
      "type": "ellipse",
      "x": 13.219555555555559,
      "y": 13.984000000000002,
      "width": 35.88977777777778,
      "height": 35.88977777777778
    },
    {
      "id": "a3fb095a-b3b8-45fe-a96e-a0fffd8c479f",
      "fillStyle": "solid",
      "strokeWidth": 0,
      "strokeStyle": "solid",
      "roughness": 0,
      "opacity": 100,
      "angle": 0,
      "strokeColor": "transparent",
      "backgroundColor": "#005ba1",
      "seed": 669353252,
      "version": 1,
      "versionNonce": 1579500522,
      "isDeleted": false,
      "groupIds": [
        "195a90c3-5403-407a-b7b7-8333a26b1f17"
      ],
      "frameId": null,
      "index": "a0",
      "roundness": null,
      "boundElements": null,
      "updated": 1775233696918,
      "link": null,
      "locked": false,
      "type": "ellipse",
      "x": 19.235555555555553,
      "y": 20.120888888888885,
      "width": 23.85777777777778,
      "height": 23.85777777777778
    },
    {
      "id": "70ca8a9d-4a90-4602-8247-7de660216227",
      "fillStyle": "solid",
      "strokeWidth": 0,
      "strokeStyle": "solid",
      "roughness": 0,
      "opacity": 100,
      "angle": 0,
      "strokeColor": "transparent",
      "backgroundColor": "#fff",
      "seed": 1166532526,
      "version": 1,
      "versionNonce": 1661330830,
      "isDeleted": false,
      "groupIds": [
        "195a90c3-5403-407a-b7b7-8333a26b1f17"
      ],
      "frameId": null,
      "index": "a0",
      "roundness": null,
      "boundElements": null,
      "updated": 1775233696918,
      "link": null,
      "locked": false,
      "type": "ellipse",
      "x": 23.655111111111108,
      "y": 24.071111111111108,
      "width": 7.168000000000003,
      "height": 7.167999999999999
    },
    {
      "id": "2a48a7cc-9e54-4407-826a-c163aad04014",
      "fillStyle": "solid",
      "strokeWidth": 0,
      "strokeStyle": "solid",
      "roughness": 0,
      "opacity": 100,
      "angle": 0,
      "strokeColor": "transparent",
      "backgroundColor": "#fff",
      "seed": 521913769,
      "version": 1,
      "versionNonce": 1920010182,
      "isDeleted": false,
      "groupIds": [
        "195a90c3-5403-407a-b7b7-8333a26b1f17"
      ],
      "frameId": null,
      "index": "a0",
      "roundness": null,
      "boundElements": null,
      "updated": 1775233696918,
      "link": null,
      "locked": false,
      "type": "ellipse",
      "x": 29.575111111111113,
      "y": 30.581333333333333,
      "width": 3.1786666666666608,
      "height": 3.1786666666666608
    }
  ]
}