{
  "status": "published",
  "id": "fca5edd9-965c-4154-b743-b99844b64d77",
  "created": 1775233696892,
  "name": "Machine Learning Studio (Classic) Web Services",
  "elements": [
    {
      "id": "38e9f049-26eb-4520-afd5-7028b4d1bf9a",
      "fillStyle": "solid",
      "strokeWidth": 0,
      "strokeStyle": "solid",
      "roughness": 0,
      "opacity": 100,
      "angle": 0,
      "strokeColor": "transparent",
      "backgroundColor": "#f2f2f2",
      "seed": 1767436205,
      "version": 1,
      "versionNonce": 1642956034,
      "isDeleted": false,
      "groupIds": [
        "21460746-7fa0-4e4f-916d-17e44bec34f7"
      ],
      "frameId": null,
      "index": "a0",
      "roundness": null,
      "boundElements": null,
      "updated": 1775233696890,
      "link": null,
      "locked": false,
      "type": "line",
      "x": 53.617777777777775,
      "y": 41.422222222222224,
      "width": 44.50553814118548,
      "height": 44.46998265602738,
      "points": [
        [
          0,
          0
        ],
        [
          -3.816874217392378,
          2.391192960005608
        ],
        [
          -7.908423988445634,
          3.927272466594805
        ],
        [
          -12.14918664813041,
          4.6240375220305685
        ],
        [
          -16.413699531417365,
          4.497287128575837
        ],
        [
          -20.576499973277155,
          3.5628202884935702
        ],
        [
          -24.512125308680417,
          1.8364360040467254
        ],
        [
          -28.095112872597813,
          -0.6660667225017517
        ],
        [
          -31.199999999999992,
          -3.92888888888889
        ],
        [
          -33.5911929600056,
          -7.745763106281268
        ],
        [
          -35.1272724665948,
          -11.83731287733453
        ],
        [
          -35.82403752203056,
          -16.078075537019306
        ],
        [
          -35.69728712857583,
          -20.342588420306264
        ],
        [
          -34.762820288493565,
          -24.505388862166054
        ],
        [
          -33.03643600404671,
          -28.44101419756932
        ],
        [
          -30.533933277498242,
          -32.024001761486716
        ],
        [
          -27.2711111111111,
          -35.128888888888895
        ],
        [
          -27.02222222222222,
          -35.306666666666665
        ],
        [
          -23.189962074183583,
          -37.67097375749084
        ],
        [
          -19.088978165032987,
          -39.178514291014544
        ],
        [
          -14.844590178750037,
          -39.845945133996814
        ],
        [
          -10.58211779931432,
          -39.68992315319673
        ],
        [
          -6.4268807107054675,
          -38.72710521537332
        ],
        [
          -2.5041985969030773,
          -36.974148187285664
        ],
        [
          1.060608858113249,
          -34.4477089356928
        ],
        [
          4.142221970363904,
          -31.16444432735381
        ],
        [
          6.506529118293208,
          -27.332184214546093
        ],
        [
          8.014069712926338,
          -23.2312003278596
        ],
        [
          8.681500619154923,
          -18.98681235152214
        ],
        [
          8.525478701870604,
          -14.724339969761527
        ],
        [
          7.56266082596506,
          -10.569102866805565
        ],
        [
          5.809703856329918,
          -6.646420726882076
        ],
        [
          3.283264657856831,
          -3.081613234218878
        ],
        [
          9.54374538903519e-08,
          -7.304376797239658e-08
        ]
      ]
    },
    {
      "id": "f21cf26d-dc20-447a-abe2-14fe237a95ec",
      "fillStyle": "solid",
      "strokeWidth": 0,
      "strokeStyle": "solid",
      "roughness": 0,
      "opacity": 100,
      "angle": 0,
      "strokeColor": "transparent",
      "backgroundColor": "#0078d4",
      "seed": 411497597,
      "version": 1,
      "versionNonce": 73472722,
      "isDeleted": false,
      "groupIds": [
        "21460746-7fa0-4e4f-916d-17e44bec34f7"
      ],
      "frameId": null,
      "index": "a0",
      "roundness": null,
      "boundElements": null,
      "updated": 1775233696891,
      "link": null,
      "locked": false,
      "type": "line",
      "x": 57.74222222222221,
      "y": 10.453333333333333,
      "width": 44.649787708372465,
      "height": 44.58680426918081,
      "points": [
        [
          0,
          0
        ],
        [
          -3.0601317328869553,
          -3.3042537930002926
        ],
        [
          -6.608254230111943,
          -5.855718905154001
        ],
        [
          -10.519400909569722,
          -7.636848658836755
        ],
        [
          -14.668605189155041,
          -8.630096376424186
        ],
        [
          -18.930900486762653,
          -8.817915380291925
        ],
        [
          -23.181320220287287,
          -8.18275899281561
        ],
        [
          -27.294897807623705,
          -6.707080536370871
        ],
        [
          -31.146666666666658,
          -4.373333333333337
        ],
        [
          -31.395555555555546,
          -4.195555555555555
        ],
        [
          -34.03833346858433,
          -1.8290105127954015
        ],
        [
          -36.23349211243486,
          0.8733068535016993
        ],
        [
          -37.962509026662815,
          3.8504345024937625
        ],
        [
          -39.20686175082386,
          7.041410393338808
        ],
        [
          -39.94802782447368,
          10.385272485194848
        ],
        [
          -40.167484787167936,
          13.821058737219905
        ],
        [
          -39.8467101784623,
          17.28780710857199
        ],
        [
          -38.96718153791246,
          20.724555558409126
        ],
        [
          -37.55486332240592,
          23.978809358461266
        ],
        [
          -35.68274134546972,
          26.914179850125844
        ],
        [
          -33.402825181618816,
          29.49386409706203
        ],
        [
          -30.767124405368133,
          31.681059162929017
        ],
        [
          -27.827648591232634,
          33.438962111386004
        ],
        [
          -24.63640731372726,
          34.73077000609219
        ],
        [
          -21.245410147366954,
          35.519679910706756
        ],
        [
          -17.70666666666666,
          35.76888888888889
        ],
        [
          -15.868806727183639,
          35.6983064958629
        ],
        [
          -14.052882828776085,
          35.47533853581879
        ],
        [
          -12.267938688292732,
          35.10308638809472
        ],
        [
          -10.523018022582303,
          34.58465143202885
        ],
        [
          -8.827164548493531,
          33.92313504695938
        ],
        [
          -7.189421982875141,
          33.12163861222448
        ],
        [
          -5.618834042575864,
          32.18326350716233
        ],
        [
          -4.124444444444432,
          31.111111111111104
        ],
        [
          -4.124444444444438,
          31.111111111111104
        ],
        [
          -0.8714313981323332,
          28.022999245861993
        ],
        [
          1.6320487866421949,
          24.460204989737665
        ],
        [
          3.3696971848255415,
          20.54567282051287
        ],
        [
          4.325214871364198,
          16.402347215962436
        ],
        [
          4.482302921204526,
          12.153172653861132
        ],
        [
          3.824662409292993,
          7.921093611983765
        ],
        [
          2.3359944105760126,
          3.8290545681051213
        ],
        [
          0,
          -4.736951571734001e-15
        ],
        [
          0,
          0
        ]
      ]
    },
    {
      "id": "42133244-73b0-4ed4-a2c4-3d3179164689",
      "fillStyle": "solid",
      "strokeWidth": 0,
      "strokeStyle": "solid",
      "roughness": 0,
      "opacity": 100,
      "angle": 0,
      "strokeColor": "transparent",
      "backgroundColor": "#ffffff",
      "seed": 1583508245,
      "version": 1,
      "versionNonce": 631998676,
      "isDeleted": false,
      "groupIds": [
        "21460746-7fa0-4e4f-916d-17e44bec34f7"
      ],
      "frameId": null,
      "index": "a0",
      "roundness": null,
      "boundElements": null,
      "updated": 1775233696891,
      "link": null,
      "locked": false,
      "type": "line",
      "x": 20.657777777777774,
      "y": 22.435555555555553,
      "width": 7.5377777777777775,
      "height": 7.573333333333332,
      "points": [
        [
          0,
          0
        ],
        [
          0.10228191403000941,
          -0.9881844449093806
        ],
        [
          0.2538340965696003,
          -1.968114940042707
        ],
        [
          0.4541398700898532,
          -2.937987349110478
        ],
        [
          0.7026825570618485,
          -3.8959975358231858
        ],
        [
          0.9989454799566696,
          -4.840341363891333
        ],
        [
          1.342411961245397,
          -5.769214697025407
        ],
        [
          1.7325653233991114,
          -6.680813398935909
        ],
        [
          2.16888888888889,
          -7.573333333333332
        ],
        [
          7.5377777777777775,
          -7.573333333333332
        ],
        [
          7.326762669540332,
          -6.639411114539481
        ],
        [
          7.1390928111747165,
          -5.700970768355426
        ],
        [
          6.974827894794815,
          -4.758450723065872
        ],
        [
          6.834027612514492,
          -3.8122894069555127
        ],
        [
          6.71675165644764,
          -2.862925248309052
        ],
        [
          6.623059718708137,
          -1.9107966754111803
        ],
        [
          6.5530114914098565,
          -0.9563421165466018
        ],
        [
          6.506666666666682,
          -1.8947806286936004e-14
        ],
        [
          0,
          0
        ]
      ]
    },
    {
      "id": "17a4e60e-4e7e-4918-9bcc-bb12b2b9981f",
      "fillStyle": "solid",
      "strokeWidth": 0,
      "strokeStyle": "solid",
      "roughness": 0,
      "opacity": 100,
      "angle": 0,
      "strokeColor": "transparent",
      "backgroundColor": "#ffffff",
      "seed": 1945898625,
      "version": 1,
      "versionNonce": 489084146,
      "isDeleted": false,
      "groupIds": [
        "21460746-7fa0-4e4f-916d-17e44bec34f7"
      ],
      "frameId": null,
      "index": "a0",
      "roundness": null,
      "boundElements": null,
      "updated": 1775233696891,
      "link": null,
      "locked": false,
      "type": "line",
      "x": 31.32444444444444,
      "y": 14.86222222222222,
      "width": 8.675555555555553,
      "height": 7.573333333333332,
      "points": [
        [
          0,
          0
        ],
        [
          7.395555555555555,
          0
        ],
        [
          7.395555555555555,
          7.573333333333332
        ],
        [
          -1.2799999999999978,
          7.573333333333332
        ],
        [
          -1.2331986469126641,
          6.614425110626633
        ],
        [
          -1.1589583918368853,
          5.657844329764799
        ],
        [
          -1.0573671330333303,
          4.704176063545412
        ],
        [
          -0.9285127687626615,
          3.754005384766028
        ],
        [
          -0.7724831972855478,
          2.8079173662242356
        ],
        [
          -0.5893663168626643,
          1.866497080717595
        ],
        [
          -0.3792500257546736,
          0.9303296010436857
        ],
        [
          -0.14222222222224445,
          7.894919286223335e-14
        ],
        [
          0,
          0
        ]
      ]
    },
    {
      "id": "2aac79e5-6ea7-4dd2-9ddf-0871666a9618",
      "fillStyle": "solid",
      "strokeWidth": 0,
      "strokeStyle": "solid",
      "roughness": 0,
      "opacity": 100,
      "angle": 0,
      "strokeColor": "transparent",
      "backgroundColor": "#ffffff",
      "seed": 1679562823,
      "version": 1,
      "versionNonce": 1804127468,
      "isDeleted": false,
      "groupIds": [
        "21460746-7fa0-4e4f-916d-17e44bec34f7"
      ],
      "frameId": null,
      "index": "a0",
      "roundness": null,
      "boundElements": null,
      "updated": 1775233696891,
      "link": null,
      "locked": false,
      "type": "line",
      "x": 41.56444444444443,
      "y": 14.86222222222222,
      "width": 8.533333333333328,
      "height": 7.57333333333333,
      "points": [
        [
          0,
          0
        ],
        [
          7.395555555555555,
          0
        ],
        [
          7.632583359087991,
          0.93032960104361
        ],
        [
          7.842699650195982,
          1.8664970807175223
        ],
        [
          8.025816530618872,
          2.807917366224163
        ],
        [
          8.181846102095985,
          3.754005384765965
        ],
        [
          8.310700466366647,
          4.704176063545358
        ],
        [
          8.41229172517021,
          5.657844329764761
        ],
        [
          8.486531980245994,
          6.614425110626611
        ],
        [
          8.533333333333328,
          7.57333333333333
        ],
        [
          0,
          7.57333333333333
        ],
        [
          0,
          0
        ]
      ]
    },
    {
      "id": "f45a5514-1308-41af-9719-20cfd4704dc0",
      "fillStyle": "solid",
      "strokeWidth": 0,
      "strokeStyle": "solid",
      "roughness": 0,
      "opacity": 100,
      "angle": 0,
      "strokeColor": "transparent",
      "backgroundColor": "#ffffff",
      "seed": 875279247,
      "version": 1,
      "versionNonce": 1280276109,
      "isDeleted": false,
      "groupIds": [
        "21460746-7fa0-4e4f-916d-17e44bec34f7"
      ],
      "frameId": null,
      "index": "a0",
      "roundness": null,
      "boundElements": null,
      "updated": 1775233696891,
      "link": null,
      "locked": false,
      "type": "line",
      "x": 38.719999999999985,
      "y": 25.279999999999998,
      "width": 8.675555555555535,
      "height": 7.537777777777781,
      "points": [
        [
          0,
          0
        ],
        [
          0,
          7.537777777777781
        ],
        [
          -7.537777777777769,
          7.537777777777781
        ],
        [
          -7.775658347809142,
          6.612137125994372
        ],
        [
          -7.986388648829208,
          5.680561827932422
        ],
        [
          -8.169878337085189,
          4.743650410954242
        ],
        [
          -8.326037068824252,
          3.8020014024221176
        ],
        [
          -8.454774500293619,
          2.8562133296983347
        ],
        [
          -8.556000287740492,
          1.9068847201451968
        ],
        [
          -8.629624087412063,
          0.9546141011249902
        ],
        [
          -8.675555555555535,
          9.473903143468002e-15
        ],
        [
          0,
          0
        ]
      ]
    },
    {
      "id": "b8167f42-59e0-4a72-bd4c-cb4797d43a12",
      "fillStyle": "solid",
      "strokeWidth": 0,
      "strokeStyle": "solid",
      "roughness": 0,
      "opacity": 100,
      "angle": 0,
      "strokeColor": "transparent",
      "backgroundColor": "#ffffff",
      "seed": 812911208,
      "version": 1,
      "versionNonce": 1755619566,
      "isDeleted": false,
      "groupIds": [
        "21460746-7fa0-4e4f-916d-17e44bec34f7"
      ],
      "frameId": null,
      "index": "a0",
      "roundness": null,
      "boundElements": null,
      "updated": 1775233696891,
      "link": null,
      "locked": false,
      "type": "line",
      "x": 41.56444444444443,
      "y": 25.279999999999998,
      "width": 8.675555555555547,
      "height": 7.537777777777698,
      "points": [
        [
          0,
          0
        ],
        [
          8.533333333333335,
          0
        ],
        [
          8.487401865189863,
          0.9546141011249586
        ],
        [
          8.41377806551829,
          1.9068847201451433
        ],
        [
          8.312552278071426,
          2.856213329698275
        ],
        [
          8.183814846602052,
          3.802001402422042
        ],
        [
          8.027656114862982,
          4.743650410954166
        ],
        [
          7.84416642660702,
          5.680561827932346
        ],
        [
          7.633436125586955,
          6.612137125994289
        ],
        [
          7.395555555555575,
          7.537777777777698
        ],
        [
          -0.14222222222221287,
          7.537777777777698
        ],
        [
          0,
          0
        ]
      ]
    },
    {
      "id": "e424edd4-be2e-4fd2-b45d-2c1b0baae468",
      "fillStyle": "solid",
      "strokeWidth": 0,
      "strokeStyle": "solid",
      "roughness": 0,
      "opacity": 100,
      "angle": 0,
      "strokeColor": "transparent",
      "backgroundColor": "#ffffff",
      "seed": 805000766,
      "version": 1,
      "versionNonce": 1280442510,
      "isDeleted": false,
      "groupIds": [
        "21460746-7fa0-4e4f-916d-17e44bec34f7"
      ],
      "frameId": null,
      "index": "a0",
      "roundness": null,
      "boundElements": null,
      "updated": 1775233696891,
      "link": null,
      "locked": false,
      "type": "line",
      "x": 52.97777777777777,
      "y": 25.279999999999998,
      "width": 7.6799999999999935,
      "height": 7.537777777777832,
      "points": [
        [
          0,
          0
        ],
        [
          6.471111111111112,
          0
        ],
        [
          6.36965246299658,
          0.9824136219108747
        ],
        [
          6.220008447980186,
          1.9568175215684012
        ],
        [
          6.022670604005447,
          2.9214749315723147
        ],
        [
          5.778130469015801,
          3.8746490845223254
        ],
        [
          5.486879580954741,
          4.814603213018162
        ],
        [
          5.149409477765718,
          5.739600549659542
        ],
        [
          4.766211697392237,
          6.647904327046186
        ],
        [
          4.337777777777761,
          7.537777777777819
        ],
        [
          -1.208888888888882,
          7.537777777777819
        ],
        [
          -0.9872915863068985,
          6.609863327904356
        ],
        [
          -0.7907684712590708,
          5.676842711356326
        ],
        [
          -0.6193915884424225,
          4.739225043992627
        ],
        [
          -0.47323298255395857,
          3.79751944167213
        ],
        [
          -0.35236469829069644,
          2.852235020253731
        ],
        [
          -0.2568587803496408,
          1.9038808955963178
        ],
        [
          -0.1867872734278156,
          0.9529661835587717
        ],
        [
          -0.14222222222221917,
          -1.2631870857957336e-14
        ],
        [
          0,
          0
        ]
      ]
    },
    {
      "id": "941e1fdc-8e53-43e3-9230-e73aa0f70f01",
      "fillStyle": "solid",
      "strokeWidth": 0,
      "strokeStyle": "solid",
      "roughness": 0,
      "opacity": 100,
      "angle": 0,
      "strokeColor": "transparent",
      "backgroundColor": "#ffffff",
      "seed": 1665912167,
      "version": 1,
      "versionNonce": 1022542465,
      "isDeleted": false,
      "groupIds": [
        "21460746-7fa0-4e4f-916d-17e44bec34f7"
      ],
      "frameId": null,
      "index": "a0",
      "roundness": null,
      "boundElements": null,
      "updated": 1775233696891,
      "link": null,
      "locked": false,
      "type": "line",
      "x": 52.97777777777777,
      "y": 22.435555555555553,
      "width": 7.537777777777806,
      "height": 7.573333333333452,
      "points": [
        [
          0,
          0
        ],
        [
          -0.0448911923523825,
          -0.9573277182109967
        ],
        [
          -0.1151932709573834,
          -1.9126155138129408
        ],
        [
          -0.21083538425739964,
          -2.8653603407468795
        ],
        [
          -0.33174668069482827,
          -3.815059152953883
        ],
        [
          -0.4778563087120662,
          -4.761208904374983
        ],
        [
          -0.6490934167515231,
          -5.703306548951243
        ],
        [
          -0.8453871532556023,
          -6.6408490406237135
        ],
        [
          -1.0666666666666944,
          -7.57333333333345
        ],
        [
          4.337777777777774,
          -7.57333333333345
        ],
        [
          4.773794518688545,
          -6.681533400024976
        ],
        [
          5.162493681915609,
          -5.7702652969437995
        ],
        [
          5.503341188551631,
          -4.841425004210827
        ],
        [
          5.795802959689328,
          -3.8969085019469354
        ],
        [
          6.039344916421428,
          -2.9386117702730163
        ],
        [
          6.233432979840623,
          -1.9684307893099628
        ],
        [
          6.3775330710396165,
          -0.9882615391786562
        ],
        [
          6.471111111111112,
          3.157967714489334e-15
        ],
        [
          0,
          0
        ]
      ]
    },
    {
      "id": "464f2528-91c5-44f9-a14d-7d5b80b92493",
      "fillStyle": "solid",
      "strokeWidth": 0,
      "strokeStyle": "solid",
      "roughness": 0,
      "opacity": 100,
      "angle": 0,
      "strokeColor": "transparent",
      "backgroundColor": "#ffffff",
      "seed": 1995536007,
      "version": 1,
      "versionNonce": 283368194,
      "isDeleted": false,
      "groupIds": [
        "21460746-7fa0-4e4f-916d-17e44bec34f7"
      ],
      "frameId": null,
      "index": "a0",
      "roundness": null,
      "boundElements": null,
      "updated": 1775233696891,
      "link": null,
      "locked": false,
      "type": "line",
      "x": 55.502222222222215,
      "y": 12.017777777777775,
      "width": 7.715555555555574,
      "height": 5.902222222222262,
      "points": [
        [
          0,
          0
        ],
        [
          -4.586666666666663,
          0
        ],
        [
          -4.873048271937572,
          -0.7893425932878984
        ],
        [
          -5.190287703939917,
          -1.5657163411102142
        ],
        [
          -5.537917407285148,
          -2.3282392639840057
        ],
        [
          -5.915469826584727,
          -3.0760293824263334
        ],
        [
          -6.322477406450105,
          -3.80820471695426
        ],
        [
          -6.75847259149273,
          -4.523883288084849
        ],
        [
          -7.222987826324072,
          -5.22218311633516
        ],
        [
          -7.715555555555574,
          -5.9022222222222585
        ],
        [
          -6.614893555760103,
          -5.382719901257102
        ],
        [
          -5.5525008972718215,
          -4.796388056078684
        ],
        [
          -4.5312422427412695,
          -4.14545924067755
        ],
        [
          -3.5539822548189477,
          -3.432166009044236
        ],
        [
          -2.62358559615537,
          -2.6587409151692816
        ],
        [
          -1.7429169294010445,
          -1.8274165130432323
        ],
        [
          -0.9148409172064917,
          -0.940425356656623
        ],
        [
          -0.14222222222221917,
          3.157967714489334e-15
        ],
        [
          0,
          0
        ]
      ]
    },
    {
      "id": "3a38e155-0fa8-4e35-8279-d0bae5a26c89",
      "fillStyle": "solid",
      "strokeWidth": 0,
      "strokeStyle": "solid",
      "roughness": 0,
      "opacity": 100,
      "angle": 0,
      "strokeColor": "transparent",
      "backgroundColor": "#ffffff",
      "seed": 591794863,
      "version": 1,
      "versionNonce": 1664002115,
      "isDeleted": false,
      "groupIds": [
        "21460746-7fa0-4e4f-916d-17e44bec34f7"
      ],
      "frameId": null,
      "index": "a0",
      "roundness": null,
      "boundElements": null,
      "updated": 1775233696891,
      "link": null,
      "locked": false,
      "type": "line",
      "x": 47.96444444444444,
      "y": 12.017777777777775,
      "width": 6.400000000000002,
      "height": 7.111111111111115,
      "points": [
        [
          0,
          0
        ],
        [
          -6.400000000000002,
          0
        ],
        [
          -6.400000000000002,
          -7.111111111111111
        ],
        [
          -5.309850133804042,
          -6.540120148789398
        ],
        [
          -4.294382219768206,
          -5.863190554392235
        ],
        [
          -3.360244945237279,
          -5.087877654447752
        ],
        [
          -2.5140869975559714,
          -4.221736775484073
        ],
        [
          -1.7625570640690662,
          -3.2723232440293324
        ],
        [
          -1.1123038321213004,
          -2.2471923866116517
        ],
        [
          -0.5699759890574366,
          -1.153899529759163
        ],
        [
          -0.14222222222221917,
          4.736951571734001e-15
        ],
        [
          0,
          0
        ]
      ]
    },
    {
      "id": "94aaeb98-0d68-416d-a751-924111e8d79d",
      "fillStyle": "solid",
      "strokeWidth": 0,
      "strokeStyle": "solid",
      "roughness": 0,
      "opacity": 100,
      "angle": 0,
      "strokeColor": "transparent",
      "backgroundColor": "#ffffff",
      "seed": 709799235,
      "version": 1,
      "versionNonce": 1665587748,
      "isDeleted": false,
      "groupIds": [
        "21460746-7fa0-4e4f-916d-17e44bec34f7"
      ],
      "frameId": null,
      "index": "a0",
      "roundness": null,
      "boundElements": null,
      "updated": 1775233696891,
      "link": null,
      "locked": false,
      "type": "line",
      "x": 38.71999999999999,
      "y": 4.9066666666666645,
      "width": 6.542222222222215,
      "height": 7.2533333333333285,
      "points": [
        [
          0,
          0
        ],
        [
          0,
          7.111111111111111
        ],
        [
          -6.542222222222215,
          7.111111111111111
        ],
        [
          -6.11282775535937,
          5.927670694602804
        ],
        [
          -5.5633059280046,
          4.807169751650426
        ],
        [
          -4.900776772812845,
          3.7576776525962505
        ],
        [
          -4.132360322439044,
          2.7872637677825463
        ],
        [
          -3.2651766095381287,
          1.9039974675515772
        ],
        [
          -2.3063456667650635,
          1.1159481222456153
        ],
        [
          -1.2629875267747808,
          0.4311851022069272
        ],
        [
          -0.14222222222221917,
          -0.14222222222221761
        ],
        [
          0,
          0
        ]
      ]
    },
    {
      "id": "dc7b2827-8eb0-4d5f-b2d3-9383e913d34a",
      "fillStyle": "solid",
      "strokeWidth": 0,
      "strokeStyle": "solid",
      "roughness": 0,
      "opacity": 100,
      "angle": 0,
      "strokeColor": "transparent",
      "backgroundColor": "#ffffff",
      "seed": 778032761,
      "version": 1,
      "versionNonce": 196983262,
      "isDeleted": false,
      "groupIds": [
        "21460746-7fa0-4e4f-916d-17e44bec34f7"
      ],
      "frameId": null,
      "index": "a0",
      "roundness": null,
      "boundElements": null,
      "updated": 1775233696891,
      "link": null,
      "locked": false,
      "type": "line",
      "x": 28.124444444444443,
      "y": 8.533333333333333,
      "width": 7.395555555555575,
      "height": 5.937777777777769,
      "points": [
        [
          0,
          0
        ],
        [
          0,
          0
        ],
        [
          0.4576878287545267,
          -0.3390997928250354
        ],
        [
          0.9249386771661596,
          -0.6642367768975596
        ],
        [
          1.401428329711267,
          -0.9752193703172369
        ],
        [
          1.8868325708661915,
          -1.2718559911837322
        ],
        [
          2.380827185107288,
          -1.553955057596705
        ],
        [
          2.883087956910913,
          -1.8213249876558184
        ],
        [
          3.393290670753408,
          -2.073774199460736
        ],
        [
          3.9111111111111287,
          -2.31111111111112
        ],
        [
          3.420783580626025,
          -1.6249156968498641
        ],
        [
          2.957920981406308,
          -0.9210376565775706
        ],
        [
          2.5229646220155737,
          -0.20031447359105115
        ],
        [
          2.116355811017412,
          0.5364163688128861
        ],
        [
          1.7385358569754126,
          1.2883173873374352
        ],
        [
          1.3899460684531528,
          2.054551098685784
        ],
        [
          1.071027754014229,
          2.8342800195611266
        ],
        [
          0.7822222222222245,
          3.626666666666649
        ],
        [
          -3.4844444444444456,
          3.626666666666649
        ],
        [
          -3.1061323041753957,
          3.1211679889054076
        ],
        [
          -2.7106560551488093,
          2.629731833845969
        ],
        [
          -2.2984201209882413,
          2.1527791321985648
        ],
        [
          -1.869828925317247,
          1.6907308146734183
        ],
        [
          -1.4252868917593686,
          1.2440078119807636
        ],
        [
          -0.9651984439381698,
          0.8130310548308238
        ],
        [
          -0.48996800547719643,
          0.39822147393382873
        ],
        [
          -6.315935428978668e-15,
          9.473903143468002e-15
        ],
        [
          0,
          0
        ]
      ]
    },
    {
      "id": "46079031-50bd-4207-9165-4fd33828610f",
      "fillStyle": "solid",
      "strokeWidth": 0,
      "strokeStyle": "solid",
      "roughness": 0,
      "opacity": 100,
      "angle": 0,
      "strokeColor": "transparent",
      "backgroundColor": "#ffffff",
      "seed": 967808009,
      "version": 1,
      "versionNonce": 152984247,
      "isDeleted": false,
      "groupIds": [
        "21460746-7fa0-4e4f-916d-17e44bec34f7"
      ],
      "frameId": null,
      "index": "a0",
      "roundness": null,
      "boundElements": null,
      "updated": 1775233696891,
      "link": null,
      "locked": false,
      "type": "line",
      "x": 20.657777777777774,
      "y": 25.28,
      "width": 7.537777777777828,
      "height": 7.537777777777986,
      "points": [
        [
          0,
          0
        ],
        [
          6.506666666666667,
          0
        ],
        [
          6.5530123879660644,
          0.9519430271414376
        ],
        [
          6.623062376219296,
          1.901989612983521
        ],
        [
          6.716756379033663,
          2.8496992917588955
        ],
        [
          6.834034144016451,
          3.7946315977002216
        ],
        [
          6.974835418774973,
          4.736346065040142
        ],
        [
          7.13909995091651,
          5.674402228011303
        ],
        [
          7.326767488048362,
          6.60835962084637
        ],
        [
          7.537777777777828,
          7.53777777777798
        ],
        [
          2.16888888888889,
          7.53777777777798
        ],
        [
          1.7236116529033279,
          6.653314532374436
        ],
        [
          1.326935262887392,
          5.748314105004324
        ],
        [
          0.9794401708383241,
          4.824793804248243
        ],
        [
          0.6817068287533882,
          3.8847709386868097
        ],
        [
          0.4343156886298326,
          2.9302628169006555
        ],
        [
          0.23784720246491511,
          1.963286747470385
        ],
        [
          0.09288182225588709,
          0.9858600389766252
        ],
        [
          3.157967714489334e-15,
          -6.315935428978668e-15
        ],
        [
          0,
          0
        ]
      ]
    },
    {
      "id": "0cef3a1a-ebb3-4e06-97d9-f619ac515194",
      "fillStyle": "solid",
      "strokeWidth": 0,
      "strokeStyle": "solid",
      "roughness": 0,
      "opacity": 100,
      "angle": 0,
      "strokeColor": "transparent",
      "backgroundColor": "#ffffff",
      "seed": 1057079537,
      "version": 1,
      "versionNonce": 1727496692,
      "isDeleted": false,
      "groupIds": [
        "21460746-7fa0-4e4f-916d-17e44bec34f7"
      ],
      "frameId": null,
      "index": "a0",
      "roundness": null,
      "boundElements": null,
      "updated": 1775233696891,
      "link": null,
      "locked": false,
      "type": "line",
      "x": 24.67555555555555,
      "y": 35.733333333333334,
      "width": 7.5377777777778,
      "height": 5.902222222222242,
      "points": [
        [
          0,
          0
        ],
        [
          4.40888888888889,
          0
        ],
        [
          4.697757331215724,
          0.788207083165509
        ],
        [
          5.016729845383982,
          1.5636882047971121
        ],
        [
          5.365360491013562,
          2.325602159177808
        ],
        [
          5.7432033277243715,
          3.0731077405905833
        ],
        [
          6.149812415136296,
          3.8053637433184235
        ],
        [
          6.584741812869247,
          4.521528961644315
        ],
        [
          7.0475455805431135,
          5.220762189851257
        ],
        [
          7.5377777777777935,
          5.902222222222242
        ],
        [
          6.440560983851867,
          5.383220620219807
        ],
        [
          5.38185026343944,
          4.797187186066625
        ],
        [
          4.364534661455701,
          4.146384096441604
        ],
        [
          3.391503222815885,
          3.433073528023625
        ],
        [
          2.4656449924351906,
          2.6595176574915813
        ],
        [
          1.5898490152288376,
          1.827978661524374
        ],
        [
          0.767004336112033,
          0.9407187168008779
        ],
        [
          -6.315935428978668e-15,
          0
        ],
        [
          0,
          0
        ]
      ]
    },
    {
      "id": "0a9ed049-9728-4587-a519-99c717fabfbd",
      "fillStyle": "solid",
      "strokeWidth": 0,
      "strokeStyle": "solid",
      "roughness": 0,
      "opacity": 100,
      "angle": 0,
      "strokeColor": "transparent",
      "backgroundColor": "#ffffff",
      "seed": 1139185856,
      "version": 1,
      "versionNonce": 969304368,
      "isDeleted": false,
      "groupIds": [
        "21460746-7fa0-4e4f-916d-17e44bec34f7"
      ],
      "frameId": null,
      "index": "a0",
      "roundness": null,
      "boundElements": null,
      "updated": 1775233696891,
      "link": null,
      "locked": false,
      "type": "line",
      "x": 32.17777777777777,
      "y": 35.733333333333334,
      "width": 6.400000000000002,
      "height": 7.288888888888891,
      "points": [
        [
          0,
          0
        ],
        [
          6.400000000000002,
          0
        ],
        [
          6.400000000000002,
          7.111111111111111
        ],
        [
          5.276637239495724,
          6.5344961893504205
        ],
        [
          4.231337194312314,
          5.845994471171119
        ],
        [
          3.271263186861404,
          5.053764184875313
        ],
        [
          2.4035785395545557,
          4.165963558765106
        ],
        [
          1.6354465748034006,
          3.1907508211425895
        ],
        [
          0.9740306150195199,
          2.1362842003098748
        ],
        [
          0.42649398261451976,
          1.010721924569048
        ],
        [
          0,
          -0.17777777777778028
        ],
        [
          0,
          0
        ]
      ]
    },
    {
      "id": "73ec8861-da97-43fd-8100-abdd63b66cda",
      "fillStyle": "solid",
      "strokeWidth": 0,
      "strokeStyle": "solid",
      "roughness": 0,
      "opacity": 100,
      "angle": 0,
      "strokeColor": "transparent",
      "backgroundColor": "#ffffff",
      "seed": 1259927344,
      "version": 1,
      "versionNonce": 241989079,
      "isDeleted": false,
      "groupIds": [
        "21460746-7fa0-4e4f-916d-17e44bec34f7"
      ],
      "frameId": null,
      "index": "a0",
      "roundness": null,
      "boundElements": null,
      "updated": 1775233696891,
      "link": null,
      "locked": false,
      "type": "line",
      "x": 41.42222222222222,
      "y": 42.84444444444444,
      "width": 6.400000000000002,
      "height": 7.395555555555549,
      "points": [
        [
          0,
          0
        ],
        [
          0,
          -7.288888888888891
        ],
        [
          6.400000000000002,
          -7.288888888888891
        ],
        [
          5.982293810135028,
          -6.085211226706557
        ],
        [
          5.440771295455861,
          -4.944455480772117
        ],
        [
          4.782727216921753,
          -3.875051152638472
        ],
        [
          4.015456335491914,
          -2.885427743858511
        ],
        [
          3.1462534121255885,
          -1.9840147559851224
        ],
        [
          2.1824132077820066,
          -1.1792416905712078
        ],
        [
          1.1312304834204066,
          -0.47953804916964926
        ],
        [
          1.2631870857957336e-14,
          0.10666666666665807
        ],
        [
          0,
          0
        ]
      ]
    },
    {
      "id": "64a8a324-8ed2-4f97-8374-b7d6ae3d0f8f",
      "fillStyle": "solid",
      "strokeWidth": 0,
      "strokeStyle": "solid",
      "roughness": 0,
      "opacity": 100,
      "angle": 0,
      "strokeColor": "transparent",
      "backgroundColor": "#ffffff",
      "seed": 1825554212,
      "version": 1,
      "versionNonce": 539414571,
      "isDeleted": false,
      "groupIds": [
        "21460746-7fa0-4e4f-916d-17e44bec34f7"
      ],
      "frameId": null,
      "index": "a0",
      "roundness": null,
      "boundElements": null,
      "updated": 1775233696891,
      "link": null,
      "locked": false,
      "type": "line",
      "x": 51.87555555555555,
      "y": 39.11111111111111,
      "width": 7.608888888888903,
      "height": 5.973333333333332,
      "points": [
        [
          0,
          0
        ],
        [
          0,
          0
        ],
        [
          -0.4782924158125878,
          0.3622514892300677
        ],
        [
          -0.9681132998141745,
          0.7078687098728171
        ],
        [
          -1.469021723587831,
          1.0365931866493585
        ],
        [
          -1.9805767587166212,
          1.3481664442808146
        ],
        [
          -2.50233747678361,
          1.642330007488264
        ],
        [
          -3.0338629493718687,
          1.918825400992849
        ],
        [
          -3.574712248064467,
          2.1773941495156475
        ],
        [
          -4.124444444444458,
          2.417777777777783
        ],
        [
          -3.623212076883798,
          1.7313365537890173
        ],
        [
          -3.151170380136073,
          1.0257953157483193
        ],
        [
          -2.708820706224142,
          0.302100436013398
        ],
        [
          -2.2966644071708133,
          -0.43880171305808185
        ],
        [
          -1.9152028349989096,
          -1.1959647591084048
        ],
        [
          -1.5649373417312518,
          -1.9684423297798805
        ],
        [
          -1.2463692793906804,
          -2.755288052714832
        ],
        [
          -0.9600000000000047,
          -3.555555555555549
        ],
        [
          3.4844444444444456,
          -3.555555555555549
        ],
        [
          3.0980975064933887,
          -3.0650748163120434
        ],
        [
          2.697065905231568,
          -2.587109489581634
        ],
        [
          2.281662169799454,
          -2.1219784826505093
        ],
        [
          1.8521988293374785,
          -1.6700007028048276
        ],
        [
          1.4089884129860921,
          -1.231495057330758
        ],
        [
          0.952343449885758,
          -0.8067804535144836
        ],
        [
          0.48257646917690206,
          -0.3961757986421743
        ],
        [
          -6.315935428978668e-15,
          6.315935428978668e-15
        ],
        [
          0,
          0
        ]
      ]
    },
    {
      "id": "c82e431d-96fc-4855-8e87-0508be1f4595",
      "fillStyle": "solid",
      "strokeWidth": 0,
      "strokeStyle": "solid",
      "roughness": 0,
      "opacity": 100,
      "angle": 0,
      "strokeColor": "transparent",
      "backgroundColor": "#2ec9eb",
      "seed": 247106480,
      "version": 1,
      "versionNonce": 1241532270,
      "isDeleted": false,
      "groupIds": [
        "21460746-7fa0-4e4f-916d-17e44bec34f7"
      ],
      "frameId": null,
      "index": "a0",
      "roundness": null,
      "boundElements": null,
      "updated": 1775233696891,
      "link": null,
      "locked": false,
      "type": "line",
      "x": 38.577777777777776,
      "y": 62.22222222222222,
      "width": 38.21833333333333,
      "height": 37.33333333333333,
      "points": [
        [
          0,
          0
        ],
        [
          -35.41333333333333,
          0
        ],
        [
          -35.80493055555555,
          -0.07972222222221918
        ],
        [
          -36.14611111111111,
          -0.2977777777777722
        ],
        [
          -36.42645833333333,
          -0.622499999999996
        ],
        [
          -36.63555555555555,
          -1.0222222222222273
        ],
        [
          -36.76298611111111,
          -1.4652777777777777
        ],
        [
          -36.79833333333333,
          -1.9199999999999968
        ],
        [
          -36.731180555555554,
          -2.3547222222222217
        ],
        [
          -36.551111111111105,
          -2.7377777777777763
        ],
        [
          -24.355555555555554,
          -20.515555555555554
        ],
        [
          -24.296696878996855,
          -20.607504044331794
        ],
        [
          -24.245474985469773,
          -20.70334433332727
        ],
        [
          -24.202035421379588,
          -20.802598198638922
        ],
        [
          -24.166523733131566,
          -20.904787416363718
        ],
        [
          -24.139085467130993,
          -21.009433762598594
        ],
        [
          -24.119866169783133,
          -21.116059013440523
        ],
        [
          -24.109011387493265,
          -21.224184944986455
        ],
        [
          -24.106666666666662,
          -21.333333333333332
        ],
        [
          -24.106666666666662,
          -33.06666666666667
        ],
        [
          -24.110146370647897,
          -33.136951262840434
        ],
        [
          -24.120456719801133,
          -33.20604539590557
        ],
        [
          -24.137404569940685,
          -33.27348277454949
        ],
        [
          -24.16079677688086,
          -33.33879710745962
        ],
        [
          -24.190440196435972,
          -33.401522103323366
        ],
        [
          -24.226141684420327,
          -33.46119147082814
        ],
        [
          -24.267708096648235,
          -33.51733891866136
        ],
        [
          -24.31494628893401,
          -33.56949815551043
        ],
        [
          -24.367105525783085,
          -33.616736347796206
        ],
        [
          -24.423252973616304,
          -33.65830276002412
        ],
        [
          -24.482922341121082,
          -33.694004248008476
        ],
        [
          -24.54564733698482,
          -33.72364766756358
        ],
        [
          -24.61096166989495,
          -33.747039874503756
        ],
        [
          -24.678399048538875,
          -33.763987724643314
        ],
        [
          -24.747493181604014,
          -33.77429807379655
        ],
        [
          -24.817777777777778,
          -33.77777777777778
        ],
        [
          -25.45777777777778,
          -33.77777777777778
        ],
        [
          -25.737239477137493,
          -33.80594991596448
        ],
        [
          -25.997531023095455,
          -33.88674891822744
        ],
        [
          -26.233076297205915,
          -34.0145986661209
        ],
        [
          -26.43829918102312,
          -34.183923041199094
        ],
        [
          -26.607623556101323,
          -34.38914592501631
        ],
        [
          -26.73547330399478,
          -34.62469119912676
        ],
        [
          -26.816272306257734,
          -34.88498274508472
        ],
        [
          -26.84444444444444,
          -35.16444444444444
        ],
        [
          -26.84444444444444,
          -35.80444444444444
        ],
        [
          -26.851758556414588,
          -35.95108703933535
        ],
        [
          -26.84365459458156,
          -36.096466088801584
        ],
        [
          -26.820507052120206,
          -36.239439868007366
        ],
        [
          -26.78269042220536,
          -36.37886665211688
        ],
        [
          -26.730579198011867,
          -36.513604716294374
        ],
        [
          -26.664547872714564,
          -36.642512335704026
        ],
        [
          -26.5849709394883,
          -36.764447785510065
        ],
        [
          -26.492222891507907,
          -36.878269340876685
        ],
        [
          -26.387968844931624,
          -36.981655223098194
        ],
        [
          -26.274357490465384,
          -37.07272224433774
        ],
        [
          -26.152488683105602,
          -37.15098656606282
        ],
        [
          -26.02346227784868,
          -37.215964349740915
        ],
        [
          -25.88837812969103,
          -37.267171756839524
        ],
        [
          -25.748336093629057,
          -37.30412494882614
        ],
        [
          -25.60443602465917,
          -37.32634008716824
        ],
        [
          -25.45777777777777,
          -37.33333333333333
        ],
        [
          -9.919999999999996,
          -37.33333333333333
        ],
        [
          -9.63888693582909,
          -37.298338089018564
        ],
        [
          -9.377800875525748,
          -37.21150454802174
        ],
        [
          -9.142125421561559,
          -37.078354353903464
        ],
        [
          -8.937244176408102,
          -36.90440915022432
        ],
        [
          -8.76854074253697,
          -36.6951905805449
        ],
        [
          -8.641398722419739,
          -36.45622028842583
        ],
        [
          -8.561201718528,
          -36.193019917427705
        ],
        [
          -8.533333333333328,
          -35.911111111111104
        ],
        [
          -8.533333333333328,
          -35.27111111111111
        ],
        [
          -8.533335354624107,
          -35.127951032111
        ],
        [
          -8.547571003635431,
          -34.986582232598714
        ],
        [
          -8.575677249696481,
          -34.84800221894959
        ],
        [
          -8.61729106213643,
          -34.713208497539
        ],
        [
          -8.672049410284457,
          -34.583198574742305
        ],
        [
          -8.73958926346973,
          -34.458969956934865
        ],
        [
          -8.81954759102142,
          -34.34152015049204
        ],
        [
          -8.911561362268703,
          -34.23184666178919
        ],
        [
          -9.014127877512976,
          -34.13197214965498
        ],
        [
          -9.125341178064463,
          -34.04354481814053
        ],
        [
          -9.244233344765581,
          -33.96700049145495
        ],
        [
          -9.369836458458735,
          -33.9027749938073
        ],
        [
          -9.501182599986338,
          -33.85130414940667
        ],
        [
          -9.637303850190808,
          -33.81302378246216
        ],
        [
          -9.777232289914561,
          -33.78836971718283
        ],
        [
          -9.920000000000003,
          -33.77777777777778
        ],
        [
          -10.595555555555553,
          -33.77777777777778
        ],
        [
          -10.664660059994894,
          -33.77433287862256
        ],
        [
          -10.732521507857083,
          -33.76394468854224
        ],
        [
          -10.798652100916636,
          -33.74682222464202
        ],
        [
          -10.862564040948055,
          -33.723174504027064
        ],
        [
          -10.923769529725849,
          -33.69321054380259
        ],
        [
          -10.981780769024526,
          -33.65713936107379
        ],
        [
          -11.036109960618592,
          -33.615169972945864
        ],
        [
          -11.08626930628256,
          -33.56751139652399
        ],
        [
          -11.131294672379441,
          -33.5149755395134
        ],
        [
          -11.17042462836506,
          -33.45856687755744
        ],
        [
          -11.203475430653153,
          -33.39878327966859
        ],
        [
          -11.230263335657442,
          -33.336122614859285
        ],
        [
          -11.250604599791659,
          -33.27108275214199
        ],
        [
          -11.26431547946952,
          -33.20416156052915
        ],
        [
          -11.27121223110476,
          -33.13585690903322
        ],
        [
          -11.271111111111107,
          -33.06666666666667
        ],
        [
          -11.271111111111107,
          -21.297777777777778
        ],
        [
          -11.27056110117547,
          -21.19243887037705
        ],
        [
          -11.260922253438789,
          -21.088137988386126
        ],
        [
          -11.24237311520508,
          -20.985436280474826
        ],
        [
          -11.215092233778382,
          -20.88489489531293
        ],
        [
          -11.179258156462717,
          -20.787074981570253
        ],
        [
          -11.135049430562118,
          -20.692537687916595
        ],
        [
          -11.08264460338061,
          -20.60184416302176
        ],
        [
          -11.02222222222222,
          -20.515555555555547
        ],
        [
          1.1733333333333336,
          -2.7377777777777763
        ],
        [
          1.353333333333334,
          -2.344513888888893
        ],
        [
          1.4199999999999968,
          -1.9049999999999978
        ],
        [
          1.383333333333332,
          -1.4496527777777777
        ],
        [
          1.2533333333333303,
          -1.0088888888888807
        ],
        [
          1.0400000000000014,
          -0.613125000000006
        ],
        [
          0.7533333333333366,
          -0.29277777777777675
        ],
        [
          0.4033333333333328,
          -0.07826388888889192
        ],
        [
          0,
          0
        ],
        [
          0,
          0
        ]
      ]
    },
    {
      "id": "3473a6b5-31bc-43c9-a64f-8d8a8bfd8c47",
      "fillStyle": "solid",
      "strokeWidth": 0,
      "strokeStyle": "solid",
      "roughness": 0,
      "opacity": 100,
      "angle": 0,
      "strokeColor": "transparent",
      "backgroundColor": "#fff",
      "seed": 606433582,
      "version": 1,
      "versionNonce": 739779365,
      "isDeleted": false,
      "groupIds": [
        "21460746-7fa0-4e4f-916d-17e44bec34f7"
      ],
      "frameId": null,
      "index": "a0",
      "roundness": null,
      "boundElements": null,
      "updated": 1775233696891,
      "link": null,
      "locked": false,
      "type": "line",
      "x": 7.964444444444445,
      "y": 57.528888888888886,
      "width": 25.994049694174223,
      "height": 22.008888888888897,
      "points": [
        [
          0,
          0
        ],
        [
          8.782222222222224,
          -12.799999999999997
        ],
        [
          8.916989603630162,
          -13.007255215929419
        ],
        [
          9.034255212751589,
          -13.223555035826651
        ],
        [
          9.133676182830216,
          -13.447785142733734
        ],
        [
          9.214909647109746,
          -13.678831219692723
        ],
        [
          9.277612738833893,
          -13.915578949745685
        ],
        [
          9.321442591246365,
          -14.156914015934666
        ],
        [
          9.346056337590868,
          -14.401722101301717
        ],
        [
          9.351111111111113,
          -14.648888888888886
        ],
        [
          9.351111111111113,
          -19.804444444444446
        ],
        [
          9.378120709279976,
          -20.00673516270422
        ],
        [
          9.442139971753896,
          -20.194412925506764
        ],
        [
          9.539218250768922,
          -20.363663314321354
        ],
        [
          9.665404898561095,
          -20.510671910617273
        ],
        [
          9.816749267366468,
          -20.631624295863812
        ],
        [
          9.989300709421084,
          -20.722706051530256
        ],
        [
          10.179108576960983,
          -20.78010275908589
        ],
        [
          10.382222222222218,
          -20.799999999999997
        ],
        [
          15.36,
          -20.799999999999997
        ],
        [
          15.563113645261232,
          -20.78010275908589
        ],
        [
          15.752921512801136,
          -20.72270605153026
        ],
        [
          15.92547295485575,
          -20.631624295863812
        ],
        [
          16.076817323661125,
          -20.51067191061728
        ],
        [
          16.203003971453295,
          -20.363663314321354
        ],
        [
          16.30008225046832,
          -20.194412925506764
        ],
        [
          16.364101512942245,
          -20.00673516270422
        ],
        [
          16.39111111111111,
          -19.804444444444446
        ],
        [
          16.39111111111111,
          -14.293333333333331
        ],
        [
          16.392568053194925,
          -14.128159642373651
        ],
        [
          16.406709253244692,
          -13.964326589580681
        ],
        [
          16.43333365404323,
          -13.802537875214512
        ],
        [
          16.472240198373374,
          -13.643497199535247
        ],
        [
          16.523227829017955,
          -13.487908262802963
        ],
        [
          16.586095488759813,
          -13.336474765277746
        ],
        [
          16.660642120381773,
          -13.189900407219687
        ],
        [
          16.746666666666666,
          -13.048888888888888
        ],
        [
          25.74222222222222,
          0
        ],
        [
          25.793734541824566,
          0.09213901053887083
        ],
        [
          25.831932474543596,
          0.18902639289280562
        ],
        [
          25.856753715095945,
          0.289282614280536
        ],
        [
          25.868135958198224,
          0.3915281419208314
        ],
        [
          25.866016898567047,
          0.4943834430324235
        ],
        [
          25.850334230919056,
          0.5964689848341196
        ],
        [
          25.821025649970842,
          0.6964052345446513
        ],
        [
          25.778028850439043,
          0.7928126593827756
        ],
        [
          25.72246847828269,
          0.882568781066728
        ],
        [
          25.656294674028103,
          0.9629881478503471
        ],
        [
          25.580683374242884,
          1.033346766755863
        ],
        [
          25.496810515494587,
          1.0929206448054678
        ],
        [
          25.4058520343508,
          1.140985789021354
        ],
        [
          25.308983867379094,
          1.1768182064257517
        ],
        [
          25.207381951147042,
          1.1996939040408783
        ],
        [
          25.102222222222224,
          1.208888888888901
        ],
        [
          0.6399999999999989,
          1.208888888888901
        ],
        [
          0.5348402710751812,
          1.1996939040408656
        ],
        [
          0.4332383548431298,
          1.1768182064257644
        ],
        [
          0.3363701878714222,
          1.140985789021354
        ],
        [
          0.24541170672763554,
          1.0929206448054678
        ],
        [
          0.16153884797934065,
          1.033346766755863
        ],
        [
          0.08592754819411633,
          0.9629881478503597
        ],
        [
          0.0197537439395382,
          0.882568781066728
        ],
        [
          -0.0358066282168197,
          0.7928126593827756
        ],
        [
          -0.07880342774861995,
          0.6964052345446513
        ],
        [
          -0.10811200869682756,
          0.5964689848341196
        ],
        [
          -0.12379467634482605,
          0.4943834430324235
        ],
        [
          -0.1259137359759974,
          0.39152814192081875
        ],
        [
          -0.11453149287371722,
          0.289282614280536
        ],
        [
          -0.08971025232137068,
          0.18902639289280562
        ],
        [
          -0.05151231960233815,
          0.09213901053888346
        ],
        [
          0,
          1.2631870857957336e-14
        ],
        [
          0,
          0
        ]
      ]
    }
  ]
}