{
  "status": "published",
  "id": "d35d2c8a-1f41-485b-bb0f-97d7ef945605",
  "created": 1775233701657,
  "name": "Service Providers",
  "elements": [
    {
      "id": "2e0c7616-da2c-462d-adb0-22e86b7a47ca",
      "fillStyle": "solid",
      "strokeWidth": 0,
      "strokeStyle": "solid",
      "roughness": 0,
      "opacity": 100,
      "angle": 0,
      "strokeColor": "transparent",
      "backgroundColor": "#54aef0",
      "seed": 240763089,
      "version": 1,
      "versionNonce": 882690061,
      "isDeleted": false,
      "groupIds": [
        "b647443b-19bb-4236-845f-d0cc55c4e9b5"
      ],
      "frameId": null,
      "index": "a0",
      "roundness": null,
      "boundElements": null,
      "updated": 1775233701657,
      "link": null,
      "locked": false,
      "type": "line",
      "x": 33.24444444444444,
      "y": 36.657777777777774,
      "width": 44.78988876778879,
      "height": 31.359999999999985,
      "points": [
        [
          0,
          0
        ],
        [
          0.03684048839800071,
          -0.3654499145473172
        ],
        [
          0.14250072212648648,
          -0.7058311669538916
        ],
        [
          0.30968885398716056,
          -1.0138519100214138
        ],
        [
          0.5311130367817327,
          -1.282220296551606
        ],
        [
          0.7994814233119251,
          -1.5036444793461783
        ],
        [
          1.1075021663794473,
          -1.6708326112068523
        ],
        [
          1.4478834187860152,
          -1.7764928449353317
        ],
        [
          1.8133333333333388,
          -1.8133333333333326
        ],
        [
          12.231111111111108,
          -1.8133333333333326
        ],
        [
          10.403469620799859,
          -3.8286247068132737
        ],
        [
          8.374425283231364,
          -5.599251180868988
        ],
        [
          6.168628306364408,
          -7.113932151858314
        ],
        [
          3.8107288981578082,
          -8.361387016139089
        ],
        [
          1.3253772665703738,
          -9.330335170069146
        ],
        [
          -1.2627763804391001,
          -10.009496010006314
        ],
        [
          -3.9290818349117873,
          -10.387588932308434
        ],
        [
          -6.648888888888895,
          -10.453333333333335
        ],
        [
          -12.268819444444448,
          -9.992152777777777
        ],
        [
          -17.188333333333336,
          -8.637222222222224
        ],
        [
          -21.41701388888889,
          -6.4314583333333335
        ],
        [
          -24.964444444444442,
          -3.4177777777777827
        ],
        [
          -27.84020833333333,
          0.3609027777777795
        ],
        [
          -30.05388888888889,
          4.861666666666659
        ],
        [
          -31.61506944444444,
          10.04159722222222
        ],
        [
          -32.53333333333333,
          15.857777777777773
        ],
        [
          -32.55877765667768,
          16.313940880319805
        ],
        [
          -32.539018453869424,
          16.767018097201607
        ],
        [
          -32.47500390536862,
          17.213828812876734
        ],
        [
          -32.3676821916353,
          17.651192411798696
        ],
        [
          -32.21800149312953,
          18.07592827842108
        ],
        [
          -32.026909990311324,
          18.4848557971974
        ],
        [
          -31.79535586364076,
          18.874794352581205
        ],
        [
          -31.524287293577867,
          19.24256332902604
        ],
        [
          -31.21799778756904,
          19.581560273289686
        ],
        [
          -30.88210038462859,
          19.886260659326272
        ],
        [
          -30.519522562568426,
          20.155100762383803
        ],
        [
          -30.13319179920047,
          20.386516857710305
        ],
        [
          -29.726035572336627,
          20.578945220553823
        ],
        [
          -29.300981359788807,
          20.73082212616237
        ],
        [
          -28.860956639368926,
          20.840583849783968
        ],
        [
          -28.408888888888892,
          20.906666666666656
        ],
        [
          0.03555555555555479,
          20.906666666666656
        ],
        [
          0,
          0
        ]
      ]
    },
    {
      "id": "68d03c3d-c089-4331-a0ab-f258158ce82b",
      "fillStyle": "solid",
      "strokeWidth": 0,
      "strokeStyle": "solid",
      "roughness": 0,
      "opacity": 80,
      "angle": 0,
      "strokeColor": "transparent",
      "backgroundColor": "#fff",
      "seed": 156822318,
      "version": 1,
      "versionNonce": 1054314585,
      "isDeleted": false,
      "groupIds": [
        "b647443b-19bb-4236-845f-d0cc55c4e9b5"
      ],
      "frameId": null,
      "index": "a0",
      "roundness": null,
      "boundElements": null,
      "updated": 1775233701657,
      "link": null,
      "locked": false,
      "type": "line",
      "x": 26.595555555555556,
      "y": 29.653333333333332,
      "width": 15.502222222222231,
      "height": 20.302222222222223,
      "points": [
        [
          0,
          0
        ],
        [
          -1.0415650597627524,
          -0.03794231037284766
        ],
        [
          -2.0737826284077445,
          -0.14982117415600743
        ],
        [
          -3.092848903273774,
          -0.3345178258609217
        ],
        [
          -4.094960081699648,
          -0.5909134999989949
        ],
        [
          -5.076312361024179,
          -0.9178894310816316
        ],
        [
          -6.033101938586175,
          -1.314326853620255
        ],
        [
          -6.961525011724442,
          -1.7791070021262794
        ],
        [
          -7.857777777777787,
          -2.3111111111111122
        ],
        [
          -0.07111111111111275,
          17.991111111111113
        ],
        [
          7.644444444444446,
          -2.204444444444445
        ],
        [
          6.770470422674994,
          -1.6939477303824015
        ],
        [
          5.865890709172257,
          -1.248472902124367
        ],
        [
          4.934353644976284,
          -0.8690720394120982
        ],
        [
          3.979507571127145,
          -0.5567972219874124
        ],
        [
          3.0050008286648837,
          -0.31270052959207023
        ],
        [
          2.014481758629573,
          -0.1378340419678731
        ],
        [
          1.0115987020612571,
          -0.033249838856584626
        ],
        [
          0,
          0
        ],
        [
          0,
          0
        ]
      ]
    },
    {
      "id": "64009eaf-03f8-4b4e-b7d7-b09784ceb612",
      "fillStyle": "solid",
      "strokeWidth": 0,
      "strokeStyle": "solid",
      "roughness": 0,
      "opacity": 100,
      "angle": 0,
      "strokeColor": "transparent",
      "backgroundColor": "#54aef0",
      "seed": 473709030,
      "version": 1,
      "versionNonce": 435477865,
      "isDeleted": false,
      "groupIds": [
        "b647443b-19bb-4236-845f-d0cc55c4e9b5"
      ],
      "frameId": null,
      "index": "a0",
      "roundness": null,
      "boundElements": null,
      "updated": 1775233701657,
      "link": null,
      "locked": false,
      "type": "ellipse",
      "x": 12.08888888888889,
      "y": 0.6044444444444441,
      "width": 29.013333333333332,
      "height": 29.013333333333332
    },
    {
      "id": "a6b9e846-4c31-4ec1-ac43-4e38ea5e2278",
      "fillStyle": "solid",
      "strokeWidth": 0,
      "strokeStyle": "solid",
      "roughness": 0,
      "opacity": 100,
      "angle": 0,
      "strokeColor": "transparent",
      "backgroundColor": "#81ce31",
      "seed": 741833766,
      "version": 1,
      "versionNonce": 1867221242,
      "isDeleted": false,
      "groupIds": [
        "b647443b-19bb-4236-845f-d0cc55c4e9b5"
      ],
      "frameId": null,
      "index": "a0",
      "roundness": null,
      "boundElements": null,
      "updated": 1775233701657,
      "link": null,
      "locked": false,
      "type": "line",
      "x": 44.76444444444444,
      "y": 55.85777777777778,
      "width": 8.319999999999999,
      "height": 8.319999999999999,
      "points": [
        [
          0,
          0
        ],
        [
          8.319999999999999,
          0
        ],
        [
          8.319999999999999,
          8.319999999999999
        ],
        [
          0,
          8.319999999999999
        ],
        [
          0,
          0
        ]
      ]
    },
    {
      "id": "314c3bee-ddcb-435e-ae61-7b7f02d1ef8c",
      "fillStyle": "solid",
      "strokeWidth": 0,
      "strokeStyle": "solid",
      "roughness": 0,
      "opacity": 100,
      "angle": 0,
      "strokeColor": "transparent",
      "backgroundColor": "#81ce31",
      "seed": 1507477388,
      "version": 1,
      "versionNonce": 277319442,
      "isDeleted": false,
      "groupIds": [
        "b647443b-19bb-4236-845f-d0cc55c4e9b5"
      ],
      "frameId": null,
      "index": "a0",
      "roundness": null,
      "boundElements": null,
      "updated": 1775233701657,
      "link": null,
      "locked": false,
      "type": "line",
      "x": 35.05777777777777,
      "y": 44.76444444444444,
      "width": 8.319999999999999,
      "height": 8.319999999999999,
      "points": [
        [
          0,
          0
        ],
        [
          8.319999999999999,
          0
        ],
        [
          8.319999999999999,
          -8.319999999999999
        ],
        [
          1.2088888888888882,
          -8.319999999999999
        ],
        [
          1.0929193052021824,
          -8.31425848843097
        ],
        [
          0.9789139856447061,
          -8.297246412328125
        ],
        [
          0.8676423108822303,
          -8.26928245959787
        ],
        [
          0.7598736615805137,
          -8.230685318146584
        ],
        [
          0.6563774184053336,
          -8.18177367588065
        ],
        [
          0.5579229620224547,
          -8.122866220706467
        ],
        [
          0.4652796730976484,
          -8.05428164053041
        ],
        [
          0.37921693229667297,
          -7.976338623258887
        ],
        [
          0.3012739150251428,
          -7.890275882457912
        ],
        [
          0.23268933484909363,
          -7.797632593533099
        ],
        [
          0.17378187967490374,
          -7.69917813715022
        ],
        [
          0.12487023740898293,
          -7.595681893975047
        ],
        [
          0.08627309595769045,
          -7.4879132446733365
        ],
        [
          0.05830914322742349,
          -7.376641569910854
        ],
        [
          0.041297067124585536,
          -7.262636250353378
        ],
        [
          0.03555555555555479,
          -7.146666666666672
        ],
        [
          0,
          0
        ]
      ]
    },
    {
      "id": "38b756fb-4795-4d4a-92da-c1ab5f43fc35",
      "fillStyle": "solid",
      "strokeWidth": 0,
      "strokeStyle": "solid",
      "roughness": 0,
      "opacity": 100,
      "angle": 0,
      "strokeColor": "transparent",
      "backgroundColor": "#81ce31",
      "seed": 442122663,
      "version": 1,
      "versionNonce": 637405226,
      "isDeleted": false,
      "groupIds": [
        "b647443b-19bb-4236-845f-d0cc55c4e9b5"
      ],
      "frameId": null,
      "index": "a0",
      "roundness": null,
      "boundElements": null,
      "updated": 1775233701657,
      "link": null,
      "locked": false,
      "type": "line",
      "x": 36.231111111111105,
      "y": 64.17777777777778,
      "width": 8.284444444444444,
      "height": 8.320000000000011,
      "points": [
        [
          0,
          0
        ],
        [
          7.111111111111111,
          0
        ],
        [
          7.111111111111111,
          -8.319999999999999
        ],
        [
          -1.1733333333333336,
          -8.319999999999999
        ],
        [
          -1.1733333333333336,
          -1.2088888888888882
        ],
        [
          -1.170948040626178,
          -1.0904901218110707
        ],
        [
          -1.156790274298367,
          -0.9738182571263678
        ],
        [
          -1.131179292610006,
          -0.8596962129499464
        ],
        [
          -1.09443435382122,
          -0.7489469073970111
        ],
        [
          -1.0468747161920962,
          -0.6423932585827288
        ],
        [
          -0.9888196379827592,
          -0.5408581846222786
        ],
        [
          -0.920588377453296,
          -0.4451646036308653
        ],
        [
          -0.8425001928638254,
          -0.35613543372366824
        ],
        [
          -0.7558411510356551,
          -0.2754250370187492
        ],
        [
          -0.6622264956729459,
          -0.2043682804242937
        ],
        [
          -0.5624692503601586,
          -0.14330883924071713
        ],
        [
          -0.45738243868172246,
          -0.09259038876843483
        ],
        [
          -0.34777908422204795,
          -0.05255660430781164
        ],
        [
          -0.23447221056558318,
          -0.023551161159262948
        ],
        [
          -0.11827484129675743,
          -0.005917734623191487
        ],
        [
          0,
          1.2631870857957336e-14
        ],
        [
          0,
          0
        ]
      ]
    },
    {
      "id": "02c3ba36-cfbb-4095-b0dd-5207e1b89271",
      "fillStyle": "solid",
      "strokeWidth": 0,
      "strokeStyle": "solid",
      "roughness": 0,
      "opacity": 100,
      "angle": 0,
      "strokeColor": "transparent",
      "backgroundColor": "#81ce31",
      "seed": 1473437269,
      "version": 1,
      "versionNonce": 1678308781,
      "isDeleted": false,
      "groupIds": [
        "b647443b-19bb-4236-845f-d0cc55c4e9b5"
      ],
      "frameId": null,
      "index": "a0",
      "roundness": null,
      "boundElements": null,
      "updated": 1775233701657,
      "link": null,
      "locked": false,
      "type": "line",
      "x": 35.05777777777777,
      "y": 54.47111111111111,
      "width": 8.319999999999999,
      "height": 8.248888888888889,
      "points": [
        [
          0,
          0
        ],
        [
          8.319999999999999,
          0
        ],
        [
          8.319999999999999,
          -8.248888888888889
        ],
        [
          0,
          -8.248888888888889
        ],
        [
          0,
          0
        ]
      ]
    },
    {
      "id": "c2109ecb-72f6-4f73-8d6e-4d2ec398de2c",
      "fillStyle": "solid",
      "strokeWidth": 0,
      "strokeStyle": "solid",
      "roughness": 0,
      "opacity": 100,
      "angle": 0,
      "strokeColor": "transparent",
      "backgroundColor": "#81ce31",
      "seed": 541807218,
      "version": 1,
      "versionNonce": 986638052,
      "isDeleted": false,
      "groupIds": [
        "b647443b-19bb-4236-845f-d0cc55c4e9b5"
      ],
      "frameId": null,
      "index": "a0",
      "roundness": null,
      "boundElements": null,
      "updated": 1775233701657,
      "link": null,
      "locked": false,
      "type": "line",
      "x": 54.435555555555545,
      "y": 64.17777777777778,
      "width": 8.248888888888889,
      "height": 8.284444444444437,
      "points": [
        [
          0,
          0
        ],
        [
          7.111111111111111,
          0
        ],
        [
          7.225872936157568,
          -0.005742201369293474
        ],
        [
          7.338616856135722,
          -0.02285894035778963
        ],
        [
          7.448553113034247,
          -0.051016176169165796
        ],
        [
          7.554891948841828,
          -0.08987986800712457
        ],
        [
          7.656843605547098,
          -0.13911597507534326
        ],
        [
          7.7536183251387705,
          -0.19839045657752447
        ],
        [
          7.844426349605492,
          -0.26736927171734554
        ],
        [
          7.928477920935923,
          -0.345718379698509
        ],
        [
          8.004204359137399,
          -0.4321403440471335
        ],
        [
          8.070357097417096,
          -0.525027315489524
        ],
        [
          8.126626547563394,
          -0.6235796340296372
        ],
        [
          8.172703121364735,
          -0.7269976396713673
        ],
        [
          8.208277230609534,
          -0.8344816724186709
        ],
        [
          8.233039287086209,
          -0.9452320722754797
        ],
        [
          8.246679702583188,
          -1.058449179245713
        ],
        [
          8.248888888888889,
          -1.1733333333333271
        ],
        [
          8.248888888888889,
          -8.284444444444437
        ],
        [
          6.315935428978668e-15,
          -8.284444444444437
        ],
        [
          0,
          0
        ]
      ]
    },
    {
      "id": "bcfa1df5-426d-40bb-8ab9-11c5edf15d42",
      "fillStyle": "solid",
      "strokeWidth": 0,
      "strokeStyle": "solid",
      "roughness": 0,
      "opacity": 100,
      "angle": 0,
      "strokeColor": "transparent",
      "backgroundColor": "#81ce31",
      "seed": 870560486,
      "version": 1,
      "versionNonce": 1178254015,
      "isDeleted": false,
      "groupIds": [
        "b647443b-19bb-4236-845f-d0cc55c4e9b5"
      ],
      "frameId": null,
      "index": "a0",
      "roundness": null,
      "boundElements": null,
      "updated": 1775233701657,
      "link": null,
      "locked": false,
      "type": "line",
      "x": 44.764444444444436,
      "y": 54.47111111111111,
      "width": 8.319999999999999,
      "height": 8.248888888888889,
      "points": [
        [
          0,
          0
        ],
        [
          8.319999999999999,
          0
        ],
        [
          8.319999999999999,
          -8.248888888888889
        ],
        [
          6.315935428978668e-15,
          -8.248888888888889
        ],
        [
          0,
          0
        ]
      ]
    },
    {
      "id": "3ebd964e-b031-497d-8967-502b2a941067",
      "fillStyle": "solid",
      "strokeWidth": 0,
      "strokeStyle": "solid",
      "roughness": 0,
      "opacity": 100,
      "angle": 0,
      "strokeColor": "transparent",
      "backgroundColor": "#81ce31",
      "seed": 1340420799,
      "version": 1,
      "versionNonce": 1413753399,
      "isDeleted": false,
      "groupIds": [
        "b647443b-19bb-4236-845f-d0cc55c4e9b5"
      ],
      "frameId": null,
      "index": "a0",
      "roundness": null,
      "boundElements": null,
      "updated": 1775233701657,
      "link": null,
      "locked": false,
      "type": "line",
      "x": 54.435555555555545,
      "y": 54.47111111111111,
      "width": 8.319999999999999,
      "height": 8.248888888888889,
      "points": [
        [
          0,
          0
        ],
        [
          8.319999999999999,
          0
        ],
        [
          8.319999999999999,
          -8.248888888888889
        ],
        [
          6.315935428978668e-15,
          -8.248888888888889
        ],
        [
          0,
          0
        ]
      ]
    },
    {
      "id": "a77fa4c6-8f94-440b-ae6f-77726a71fb73",
      "fillStyle": "solid",
      "strokeWidth": 0,
      "strokeStyle": "solid",
      "roughness": 0,
      "opacity": 100,
      "angle": 0,
      "strokeColor": "transparent",
      "backgroundColor": "#81ce31",
      "seed": 352323817,
      "version": 1,
      "versionNonce": 73332921,
      "isDeleted": false,
      "groupIds": [
        "b647443b-19bb-4236-845f-d0cc55c4e9b5"
      ],
      "frameId": null,
      "index": "a0",
      "roundness": null,
      "boundElements": null,
      "updated": 1775233701657,
      "link": null,
      "locked": false,
      "type": "line",
      "x": 54.435555555555545,
      "y": 36.44444444444444,
      "width": 8.319999999999999,
      "height": 8.319999999999999,
      "points": [
        [
          0,
          0
        ],
        [
          0,
          8.319999999999999
        ],
        [
          8.319999999999999,
          8.319999999999999
        ],
        [
          8.319999999999999,
          1.2088888888888882
        ],
        [
          8.31779081369431,
          1.0940047348012802
        ],
        [
          8.304150398197319,
          0.9807876278310408
        ],
        [
          8.279388341720644,
          0.870037227974232
        ],
        [
          8.243814232475831,
          0.7625531952269284
        ],
        [
          8.197737658674491,
          0.6591351895851858
        ],
        [
          8.141468208528194,
          0.5605828710450851
        ],
        [
          8.075315470248508,
          0.4676958996026883
        ],
        [
          7.999589032047033,
          0.3812739352540575
        ],
        [
          7.915537460716601,
          0.3029248272729003
        ],
        [
          7.82472943624988,
          0.23394601213307925
        ],
        [
          7.72795471665822,
          0.17467153063090438
        ],
        [
          7.626003059952937,
          0.12543542356268567
        ],
        [
          7.5196642241453695,
          0.0865717317247269
        ],
        [
          7.409727967246845,
          0.05841449591335074
        ],
        [
          7.296984047268678,
          0.04129775692485459
        ],
        [
          7.1822222222222205,
          0.03555555555555479
        ],
        [
          0,
          0
        ]
      ]
    },
    {
      "id": "41b02b72-3746-4c55-92b9-5d7cb2ced56a",
      "fillStyle": "solid",
      "strokeWidth": 0,
      "strokeStyle": "solid",
      "roughness": 0,
      "opacity": 100,
      "angle": 0,
      "strokeColor": "transparent",
      "backgroundColor": "#81ce31",
      "seed": 364625225,
      "version": 1,
      "versionNonce": 43895276,
      "isDeleted": false,
      "groupIds": [
        "b647443b-19bb-4236-845f-d0cc55c4e9b5"
      ],
      "frameId": null,
      "index": "a0",
      "roundness": null,
      "boundElements": null,
      "updated": 1775233701657,
      "link": null,
      "locked": false,
      "type": "line",
      "x": 44.764444444444436,
      "y": 44.76444444444444,
      "width": 8.319999999999999,
      "height": 8.319999999999999,
      "points": [
        [
          0,
          0
        ],
        [
          8.319999999999999,
          0
        ],
        [
          8.319999999999999,
          -8.319999999999999
        ],
        [
          6.315935428978668e-15,
          -8.319999999999999
        ],
        [
          0,
          0
        ]
      ]
    }
  ]
}